main.py
gittsinit/__init__.py
gittsinit-1.0.0.dist-info/licenses/LICENCE
gittsinit-1.0.0.dist-info/METADATA
gittsinit-1.0.0.dist-info/WHEEL
gittsinit-1.0.0.dist-info/entry_points.txt
gittsinit-1.0.0.dist-info/top_level.txt
gittsinit-1.0.0.dist-info/RECORD
