Metadata-Version: 2.4
Name: gittsinit
Version: 1.0.0
Summary: A powerful Python script that automatically creates Git commits with timestamps based on file creation or modification dates
Author: bxff
Maintainer: bxff
License: MIT License
Project-URL: Homepage, https://github.com/bxff/git-commit-on-filestamp
Project-URL: Documentation, https://github.com/bxff/git-commit-on-filestamp#readme
Project-URL: Repository, https://github.com/bxff/git-commit-on-filestamp.git
Project-URL: Bug Reports, https://github.com/bxff/git-commit-on-filestamp/issues
Keywords: git,commit,timestamp,version-control,automation
Classifier: Development Status :: 5 - Production/Stable
Classifier: Intended Audience :: Developers
Classifier: Topic :: Software Development :: Version Control :: Git
Classifier: Programming Language :: Python :: 3
Classifier: Programming Language :: Python :: 3.8
Classifier: Programming Language :: Python :: 3.9
Classifier: Programming Language :: Python :: 3.10
Classifier: Programming Language :: Python :: 3.11
Classifier: Programming Language :: Python :: 3.12
Classifier: Operating System :: OS Independent
Requires-Python: >=3.8
License-File: LICENCE
Requires-Dist: requests>=2.25.0
Requires-Dist: python-dotenv>=0.19.0
Provides-Extra: dev
Requires-Dist: pytest>=6.0; extra == "dev"
Requires-Dist: black>=21.0; extra == "dev"
Requires-Dist: flake8>=3.8; extra == "dev"
Requires-Dist: mypy>=0.800; extra == "dev"
Requires-Dist: types-requests>=2.25.0; extra == "dev"
Dynamic: license-file
